pysvg_cl3/DXFPainter.py
pysvg_cl3/GDSPainter.py
pysvg_cl3/Painter.py
pysvg_cl3/Path.py
pysvg_cl3/SVGPainter.py
pysvg_cl3/__init__.py
pysvg_cl3/matrix.py
pysvg_cl3/svg.py
pysvg_cl3-0.0.4.dist-info/LICENSE
pysvg_cl3-0.0.4.dist-info/METADATA
pysvg_cl3-0.0.4.dist-info/WHEEL
pysvg_cl3-0.0.4.dist-info/top_level.txt
pysvg_cl3-0.0.4.dist-info/RECORD
